odoo/addons/delivery_carrier_shipping_label/README.rst
odoo/addons/delivery_carrier_shipping_label/__init__.py
odoo/addons/delivery_carrier_shipping_label/__manifest__.py
odoo/addons/delivery_carrier_shipping_label/i18n/delivery_carrier_shipping_label.pot
odoo/addons/delivery_carrier_shipping_label/i18n/it.po
odoo/addons/delivery_carrier_shipping_label/models/__init__.py
odoo/addons/delivery_carrier_shipping_label/models/delivery_carrier.py
odoo/addons/delivery_carrier_shipping_label/models/shipping_label.py
odoo/addons/delivery_carrier_shipping_label/models/stock_picking.py
odoo/addons/delivery_carrier_shipping_label/readme/CONTRIBUTORS.md
odoo/addons/delivery_carrier_shipping_label/readme/DESCRIPTION.md
odoo/addons/delivery_carrier_shipping_label/readme/USAGE.md
odoo/addons/delivery_carrier_shipping_label/security/ir.model.access.csv
odoo/addons/delivery_carrier_shipping_label/static/description/icon.png
odoo/addons/delivery_carrier_shipping_label/static/description/index.html
odoo/addons/delivery_carrier_shipping_label/tests/__init__.py
odoo/addons/delivery_carrier_shipping_label/tests/test_shipping_label.py
odoo/addons/delivery_carrier_shipping_label/views/delivery_carrier.xml
odoo/addons/delivery_carrier_shipping_label/views/delivery_carrier_option.xml
odoo/addons/delivery_carrier_shipping_label/views/delivery_carrier_template_option.xml
odoo/addons/delivery_carrier_shipping_label/views/stock_picking.xml
odoo_addon_delivery_carrier_shipping_label-18.0.1.0.0.4.dist-info/METADATA
odoo_addon_delivery_carrier_shipping_label-18.0.1.0.0.4.dist-info/WHEEL
odoo_addon_delivery_carrier_shipping_label-18.0.1.0.0.4.dist-info/top_level.txt
odoo_addon_delivery_carrier_shipping_label-18.0.1.0.0.4.dist-info/RECORD
